{
  "name": "Isabelle Cohen",
  "age": 62,
  "address": {
    "street": "Okazo Grove",
    "city": "Maozcu",
    "state": "LA",
    "zip": "65590"
  },
  "contact": {
    "phone": "(739) 965-4418",
    "servicePhone": "800658838"
  },
  "birthday": "1959-04-11T21:46:37.254Z",
  "ip": "70.20.192.106",
  "foo": "bar",
  "profile": {
    "about": "Ubataso onnefic coro vuham ih joltez co pu ha ebara azi eko nubetos nig jokivi ojulicu. Kecuso werukula ibitez lojhek gevzobav hiujojag merkiloh ekcede geto wi mualo lo sam roowo imotuble comzinrew. Wileze kidtep pitan usimazpuh nud vi difekgim elkat cel udwufo aluoka kinerido zac rizcuwbum no deg. Hus cilcufej nueg ruhmokifa davhen cer ig gudagu movoh harar coaclit mud ofijejcod piwmuh ca moupha ja. Mewcecgo kap da sobami gugo iwunabu oh ezugiw bum irevwif bino jac udli vew.",
    "bio": "En ipajicev nokducki rurraz visvauv ogu rahbun ka pokevlo vesge anaizov fokupji mosviwwu kubgejse. Bedah tufajbas oneziba fuwebzin worohi suhanuof igadab im unjoh aku lemgucar dulgoh. Wo obeamwi ifdavoc cevutup zigegso uwosut hu soruc boiwwa ginuhkej selno zukno tivirmo sotaro odu ike. Paneb gi we heade jiac wipon ka forig lulir te oso om ciwvufe imaugdol luv ahito. Iwidef lafuc iljavic hehsipose ujo igkamav pegful bav inemaafi lahos babse vosi rujvup ehaneb hujdih fikudwi."
  },
  "apiKey": "9f0ac68378add80450495ef94237ca90942c316df7d6c6110e435c9583052cba",
  "currency": {
    "code": "MDL",
    "name": "Moldova Leu"
  }
}