{
  "name": "Fanny Waters",
  "age": 55,
  "address": {
    "street": "Pipuze Loop",
    "city": "Vasagbug",
    "state": "NC",
    "zip": "33335"
  },
  "contact": {
    "phone": "(631) 851-5859",
    "servicePhone": "800711814"
  },
  "birthday": "1986-10-03T12:37:42.954Z",
  "ip": "205.188.38.42",
  "foo": "bar",
  "profile": {
    "about": "Ri bastof felmioto oj bo razledid la nedowec ibu fi cut ogi rotohoj misidiora fohmad utabohwap tiwdi ri. Hat pigif pajefte motut izo kar citudi piv be otuca jibjil ri hig zutas encuhki mas kebeto bisfiw. Pajiv haw rigamuite pazihupi nictukpev kip etomir vesfaiz anelfer rekefo buwgubup uru hu. Jaudomi be befel fifo so jot depepanek lalikja kozkifi tojebzu tunenvuh zazah pac ga. Uvamis iwobi ataojka ruho kivuwjen kimvuj hidwav narjumwif pujo ja bigofilu bajekeh. Mobpuwja lus zi gi ni gatu miamiib belgef vilbiura tesiako tuknav ru.",
    "bio": "Dap kope rise be nezpo worrowha ogit rowuz menege alrod apu takgihiw. Tos epumejuto ilhu pefala aha zioglok polpu win micajlim re nuvgip vawmac rotbulev leton bi cul ta iturieri. Toka jaruzac jajid hovvu jip fen giotol tosbarpa ubzo der pewujozo ci fepji. Hozofemo buvi tibdiil capi coke gimocut mof wohiv du bi van fugahe cute dobefo dola babik nevo. Niozora hisuh siifzeg ro nofzate cep cah azosa but refallum woduuh jeef. Joup tebev ig kuvaz dizomize atadi ev zaw siidvup mahigu owipu oke cobasewi hu tuf van gof."
  },
  "apiKey": "a6840fe01aaab81ba86ea3afdc08dff3af51a1ba67dd4a7a3dd4a2167f288030",
  "currency": {
    "code": "BYR",
    "name": "Belarus Ruble"
  }
}