{
  "name": "Estelle Harmon",
  "age": 64,
  "address": {
    "street": "Haltam Glen",
    "city": "Nuusle",
    "state": "NE",
    "zip": "10993"
  },
  "contact": {
    "phone": "(926) 926-1582",
    "servicePhone": "800156482"
  },
  "birthday": "1970-01-01T04:03:01.419Z",
  "ip": "12.31.111.170",
  "foo": "bar",
  "profile": {
    "about": "Lieju vevis nu tiolifo vulieva atuer upoakigu pogrirca cukrugemo vagnad riurubiv juj ju utieta lobakpo zedupar lenesdi wal. Wibocoko ozilamwo tipli opaanmi lob iwjeugi etewos aghawu ek pavcodpen icvipni can feelote oziredop woceg. Cok et ru weglo vapeato lefoted onvac atfeov cejiamu mi ranujopis okitaz udacduj faele uja pij.",
    "bio": "Ucuse evi ciwot elijim mar da pagibaf obunafku hat foldawi volfezwu dew urbaco pidnurij taoztam. Fin jud bulis lup bo ejemon ku elioze lubih usivi bonvuog me bef huzmoh utukamvuk. Je uwvabeh han joega ka luanzi tipifu fisa zazkivpij loin surek oro atnihvil. Vagoit ode disdojlih katogsit kenta otjuvzu re opid kusata ozejgul movjo zifal vifkaj. Gahewgoc tahesoci verofki dujiwi heckacli za surtarda voanetah gehwiz dabzajoj oloopme ri. Wulti feje igulauki op bif moz dajus teju jom caczu raruab biluuv ammek vihiwzon adnor."
  },
  "apiKey": "57458271524bcd55af961e881923bfcfa5f6b5007c3eaa3bbf79f86d19f3c8c5",
  "currency": {
    "code": "CLP",
    "name": "Chile Peso"
  }
}