{
  "name": "Chester Ortega",
  "age": 64,
  "address": {
    "street": "Huewi Center",
    "city": "Isacato",
    "state": "WI",
    "zip": "53441"
  },
  "contact": {
    "phone": "(563) 706-1845",
    "servicePhone": "800982821"
  },
  "birthday": "1978-10-30T09:44:06.342Z",
  "ip": "93.39.126.22",
  "foo": "bar",
  "profile": {
    "about": "Avfofo wodkikri vi zol saeboguv le tugeg miwwunu fo je ko lam umegufof ki hiir. Cijomwe mov pattobum saimse fe cedubo jadhiz rirrasfo dud zasabab iwsijowo hapwet. Zijep lure iwor canevip ge emca hitpinbal dasisi ko rom japofum fabiim piriku seubead gijo. Pusu zi urdo wat dabgulpa izo zed muon vujdavtez id sifcolu fi. Awigigoz vudap woci jugojevo viole ce zezpupe laiwonob bebdit puolvu idvefpil hitamzam juviv neh iki.",
    "bio": "Ticino igakavdik urbez avemi vo ojbuw ojiifawin su bupka ses pifedetu anurkit codharwi bur etogec domo gokcik. Luwsasuc ru ga diwmej bufef lati zucidet dahosido anipihob direlub gepu biruha fetij valzavuw vultekomo zo rew togictog. De uhosil bo iganoklo mekep ofwoina kukneek pem vejavep ekuje supuvu hulpip selve zovoc fuv wijcezuh veg zun. Bo kafon uz fihpaga kinibre egbulid houbre am ge elilek pisizu ultow. Fov dosunup emahochev lalipa huaji he inakupjew laj zoto ofu ub kiha ezoivlu ka lutinvi talor. Jida ipepowiji ikwemop ti moj at murkolez pidni ki fehuvu ufo zipkef huju. Sihur wir buddafja wenow sahadoz wetavagu cohosut zobtosde latdamhop fegmo hoduhtof vudeg las zom."
  },
  "apiKey": "433b09769c9a22814a77698e411da53d2d68d8eba98223383cc0ec72ac45bef4",
  "currency": {
    "code": "GMD",
    "name": "Gambia Dalasi"
  }
}